thermal_tyre_driver/__init__.py
thermal_tyre_driver/driver.py
thermal_tyre_driver/py.typed
thermal_tyre_driver-0.1.1.dist-info/licenses/LICENSE
thermal_tyre_driver-0.1.1.dist-info/METADATA
thermal_tyre_driver-0.1.1.dist-info/WHEEL
thermal_tyre_driver-0.1.1.dist-info/top_level.txt
thermal_tyre_driver-0.1.1.dist-info/RECORD
