Metadata-Version: 2.4
Name: thermal-tyre-driver
Version: 0.1.1
Summary: Thermal tyre analysis toolkit for MLX90640 sensors.
Author: Sam Conway
License: GNU GENERAL PUBLIC LICENSE
Project-URL: Homepage, https://github.com/samskjord/thermal-tyre-driver
Project-URL: Issues, https://github.com/samskjord/thermal-tyre-driver/issues
Keywords: tyre,tire,thermal,racing,sensors,mlx90640
Classifier: Development Status :: 4 - Beta
Classifier: Intended Audience :: Developers
Classifier: Intended Audience :: Science/Research
Classifier: License :: OSI Approved :: MIT License
Classifier: Operating System :: POSIX :: Linux
Classifier: Programming Language :: Python :: 3
Classifier: Programming Language :: Python :: 3.8
Classifier: Programming Language :: Python :: 3.9
Classifier: Programming Language :: Python :: 3.10
Classifier: Programming Language :: Python :: 3.11
Classifier: Topic :: Scientific/Engineering
Classifier: Topic :: Scientific/Engineering :: Information Analysis
Classifier: Topic :: Software Development :: Embedded Systems
Requires-Python: >=3.8
License-File: LICENSE
Requires-Dist: numpy>=1.23
Requires-Dist: scipy>=1.10
Requires-Dist: adafruit-circuitpython-mlx90640>=1.2
Requires-Dist: adafruit-blinka>=8.34
Dynamic: license-file
